wsp_tasha_toolbox/__init__.py
wsp_tasha_toolbox/_version.py
wsp_tasha_toolbox/common/__init__.py
wsp_tasha_toolbox/common/activity_pairs.py
wsp_tasha_toolbox/common/enums_data.py
wsp_tasha_toolbox/common/enums_microsim.py
wsp_tasha_toolbox/common/enums_model.py
wsp_tasha_toolbox/common/enums_tts2016.py
wsp_tasha_toolbox/data_model/__init__.py
wsp_tasha_toolbox/data_model/data_model.py
wsp_tasha_toolbox/data_model/schema.py
wsp_tasha_toolbox/io/__init__.py
wsp_tasha_toolbox/io/tts.py
wsp_tasha_toolbox/processing/__init__.py
wsp_tasha_toolbox/processing/tlfd.py
wsp_tasha_toolbox-0.1.4.dist-info/licenses/LICENSE
wsp_tasha_toolbox-0.1.4.dist-info/METADATA
wsp_tasha_toolbox-0.1.4.dist-info/WHEEL
wsp_tasha_toolbox-0.1.4.dist-info/top_level.txt
wsp_tasha_toolbox-0.1.4.dist-info/RECORD
