Metadata-Version: 2.4
Name: wsp-tasha-toolbox
Version: 0.1.4
Summary: Python tools for working with TASHA-based models
Author-email: Brian Cheung <brian.cheung@wsp.com>
Project-URL: Homepage, https://github.com/sap-toronto/wsp-tasha-toolbox
Project-URL: Issues, https://github.com/sap-toronto/wsp-tasha-toolbox/issues
Classifier: Development Status :: 4 - Beta
Classifier: License :: OSI Approved :: BSD License
Classifier: Operating System :: OS Independent
Classifier: Programming Language :: Python :: 3
Requires-Python: >=3.10
License-File: LICENSE
Requires-Dist: geopandas>=1.0.1
Requires-Dist: numpy>=1.26.2
Requires-Dist: pandas>=2.0.2
Requires-Dist: pandera>=0.24.0
Requires-Dist: pyproj>=3.5.0
Requires-Dist: wsp-balsa>=2.1.0
Dynamic: license-file
